translate_util/__init__.py
translate_util/base_translate.py
translate_util/common_request.py
translate_util/translate_baidu.py
translate_util/translate_google.py
translate_util/translate_iciba.py
translate_util/translate_tool.py
translate_util/translate_youdao.py
translate_util-1.1.4.dist-info/LICENSE.rst
translate_util-1.1.4.dist-info/METADATA
translate_util-1.1.4.dist-info/WHEEL
translate_util-1.1.4.dist-info/top_level.txt
translate_util-1.1.4.dist-info/RECORD
