Metadata-Version: 2.1
Name: translate-util
Version: 1.1.4
Summary: translate tool support(google)
Home-page: https://github.com/abo123456789/translate_util
Author: cc
Author-email: abcdef123456chen@sohu.com
Maintainer: cc
Maintainer-email: abcdef123456chen@sohu.com
License: MIT License
Platform: all
Classifier: Development Status :: 4 - Beta
Classifier: Operating System :: OS Independent
Classifier: Intended Audience :: Developers
Classifier: License :: OSI Approved :: MIT License
Classifier: Programming Language :: Python
Classifier: Programming Language :: Python :: Implementation
Classifier: Programming Language :: Python :: 3.6
Classifier: Topic :: Software Development :: Libraries
Requires-Dist: requests (>=2.22.0)
Requires-Dist: retrying (>=1.3.3)
Requires-Dist: loguru (>=0.3.2)
Requires-Dist: PyExecJS (>=1.5.1)
